{"assets/icons/busca.svg":["assets/icons/busca.svg"],"assets/icons/chevrondown.svg":["assets/icons/chevrondown.svg"],"assets/icons/chevronleft.svg":["assets/icons/chevronleft.svg"],"assets/icons/chevronright.svg":["assets/icons/chevronright.svg"],"assets/icons/chevronup.svg":["assets/icons/chevronup.svg"],"assets/icons/conta.svg":["assets/icons/conta.svg"],"assets/icons/delete.svg":["assets/icons/delete.svg"],"assets/icons/seta_para_baixo.svg":["assets/icons/seta_para_baixo.svg"],"assets/images/aviao.png":["assets/images/aviao.png"],"assets/images/show.jpg":["assets/images/show.jpg"],"assets/images/store.jpg":["assets/images/store.jpg"],"packages/cupertino_icons/assets/CupertinoIcons.ttf":["packages/cupertino_icons/assets/CupertinoIcons.ttf"]}